rhymetagger/__init__.py
rhymetagger/tagger.py
rhymetagger/models/cs.json
rhymetagger/models/de.json
rhymetagger/models/en.json
rhymetagger/models/es.json
rhymetagger/models/fr.json
rhymetagger/models/it.json
rhymetagger/models/pt.json
rhymetagger/models/ru.json
rhymetagger/models/sl.json
rhymetagger-1.0.0.dist-info/licenses/LICENSE.txt
rhymetagger-1.0.0.dist-info/METADATA
rhymetagger-1.0.0.dist-info/WHEEL
rhymetagger-1.0.0.dist-info/top_level.txt
rhymetagger-1.0.0.dist-info/RECORD
