Metadata-Version: 2.4
Name: rhymetagger
Version: 1.0.0
Summary: A simple collocation-driven recognition of rhymes
Home-page: https://github.com/versotym/rhymetagger
Download-URL: https://github.com/versotym/rhymeTagger/archive/v1.0.0.tar.gz
Author: Petr Plechac
Author-email: plechac@ucl.cas.cz
License: MIT
Keywords: poetry,rhyme,versification
Classifier: Development Status :: 4 - Beta
Classifier: Intended Audience :: Developers
Classifier: Topic :: Text Processing :: Linguistic
Classifier: License :: OSI Approved :: MIT License
Classifier: Programming Language :: Python :: 3
Classifier: Programming Language :: Python :: 3.1
Classifier: Programming Language :: Python :: 3.2
Classifier: Programming Language :: Python :: 3.3
Classifier: Programming Language :: Python :: 3.4
Classifier: Programming Language :: Python :: 3.5
Classifier: Programming Language :: Python :: 3.6
Classifier: Programming Language :: Python :: 3.7
Classifier: Programming Language :: Python :: 3.8
Classifier: Programming Language :: Python :: 3.9
Classifier: Programming Language :: Python :: 3.10
Classifier: Programming Language :: Python :: 3.11
Classifier: Programming Language :: Python :: 3.12
License-File: LICENSE.txt
Requires-Dist: ujson
Requires-Dist: nltk
Dynamic: author
Dynamic: author-email
Dynamic: classifier
Dynamic: description
Dynamic: description-content-type
Dynamic: download-url
Dynamic: home-page
Dynamic: keywords
Dynamic: license
Dynamic: license-file
Dynamic: requires-dist
Dynamic: summary
